main.py
src/db/readme.md
src/pymibig/__about__.py
src/pymibig/__init__.py
src/pymibig/args_class.py
src/pymibig/console.py
src/pymibig/constants.py
src/pymibig/download_aa.py
src/pymibig/download_json.py
src/pymibig/download_nucl.py
src/pymibig/get_args.py
src/pymibig/save_aa.py
src/pymibig/save_access_codes.py
src/pymibig/save_nucl.py
src/pymibig/treat_args.py
pymibig-1.4.0.dist-info/METADATA
pymibig-1.4.0.dist-info/WHEEL
pymibig-1.4.0.dist-info/entry_points.txt
pymibig-1.4.0.dist-info/licenses/LICENSE.txt
pymibig-1.4.0.dist-info/RECORD
