Metadata-Version: 2.3
Name: pymibig
Version: 1.4.0
Summary: A small tool to download, match and save sequences from MIBiG.
Project-URL: Documentation, https://github.com/Godrigos/pyMIBiG#readme
Project-URL: Issues, https://github.com/Godrigos/pyMIBiG/issues
Project-URL: Source, https://github.com/Godrigos/pyMIBiG
Author-email: Rodrigo Aluizio <r.aluizio@gmail.com>
License: LGPL-3.0-or-later
Keywords: Biosynthetic Gene Cluster,MIBiG,Secondary Metabolites,bioinformatics
Classifier: Development Status :: 5 - Production/Stable
Classifier: Programming Language :: Python
Classifier: Programming Language :: Python :: 3.12
Classifier: Topic :: Scientific/Engineering :: Bio-Informatics
Requires-Python: >=3.10
Requires-Dist: biopython~=1.84
Requires-Dist: bio~=1.7
Requires-Dist: pandas~=2.2
Requires-Dist: requests~=2.32
Requires-Dist: rich~=13.9
